Workbook
Name Slicer_Payment_Method: #N/A
Name Slicer_Shipped: #N/A

Sheet Raw_Data
A1: OrderID | B1: CustomerName | C1: CustomerEmail | D1: City | E1: OrderDate | F1: Product | G1: Quantity | H1: Discount(%) | I1: TotalPrice($) | J1: PaymentMethod | K1: Shipped
A2: bdd640fb-0667-4ad1-9c80-317fa3b1799d | B2: Daniel Doyle | C2: garzaanthony@example.org | D2: East William | E2: 45411 | F2: Smartphone | G2: 3 | H2: 5 | I2: 2280 | J2: Credit Card | K2: Yes
A3: b38a088c-a65e-4389-b74d-0fb132e70629 | B3: Connie Lawrence | C3: blakeerik@example.com | D3: Joshuaborough | E3: 45752 | F3: Keyboard | G3: 4 | H3: 0 | I3: 400 | J3: Debit Card | K3: Yes
A4: 6142ea7d-17be-4111-9a2a-73ed562b0f79 | B4: Ryan Munoz | C4: blairamanda@example.com | D4: New Kellystad | E4: 45613 | F4: Monitor | G4: 3 | H4: 0 | I4: 900 | J4: Debit Card | K4: Yes
A5: a9488d99-0bbb-4599-91ce-5dd2b45ed1f0 | B5: Dylan Miller | C5: michellejames@example.com | D5: Franciscostad | E5: 45478 | F5: Smartphone | G5: 1 | H5: 5 | I5: 760 | J5: Google Pay | K5: Yes
A6: aefcfad8-efc8-4849-b3aa-7efe4458a885 | B6: Lisa Jackson | C6: frankgray@example.net | D6: Lake Mark | E6: 45683 | F6: Smartphone | G6: 2 | H6: 0 | I6: 1600 | J6: Google Pay | K6: Yes
A7: 0837b8a3-d261-47ab-baa2-e4f90e51f30d | B7: Jennifer Jones | C7: jason76@example.net | D7: Thomasberg | E7: 45492 | F7: Desk Chair | G7: 2 | H7: 0 | I7: 400 | J7: Credit Card | K7: Yes
A8: bf3c4c06-4343-48bc-89fa-6a688fb5d27b | B8: Stephanie Ross | C8: wendytaylor@example.com | D8: Port Brandonville | E8: 45457 | F8: Laptop | G8: 1 | H8: 5 | I8: 1140 | J8: Credit Card | K8: Yes
A9: 6c12ace8-ae34-4454-8ac5-b68c28f49481 | B9: Janice Carlson | C9: jrice@example.org | D9: Lake Nicoleview | E9: 45683 | F9: Monitor | G9: 1 | H9: 0 | I9: 300 | J9: Debit Card | K9: Yes
A10: 6f4cc69a-4b22-4308-9c8e-aee95715bd6f | B10: Aaron Bowen | C10: teresa28@example.org | D10: Meaganhaven | E10: 45624 | F10: External Hard Drive | G10: 3 | H10: 0 | I10: 270 | J10: Google Pay | K10: Yes
A11: 295b4715-c333-4861-9fb8-d16c2720797d | B11: Paula Moreno | C11: georgetracy@example.org | D11: Natashaport | E11: 45489 | F11: Laptop | G11: 4 | H11: 0 | I11: 4800 | J11: Google Pay | K11: Yes
A12: f26b4776-913e-4de2-a0c5-3cb83da9c2a9 | B12: Nicholas Cabrera | C12: davidalvarez@example.net | D12: West Allison | E12: 45624 | F12: Monitor | G12: 3 | H12: 5 | I12: 855 | J12: Google Pay | K12: Yes
A13: 8a0f4efb-edcd-465e-b638-6821f6e07cc0 | B13: Melissa Marquez | C13: pcarney@example.com | D13: Lammouth | E13: 45446 | F13: Desk Chair | G13: 4 | H13: 0 | I13: 800 | J13: Debit Card | K13: Yes
... A10001: 6b376ab7-babe-4a22-b09d-01d5164cb33f | B10001: Charles Riley | C10001: montoyanancy@example.org | D10001: North Williamchester | E10001: 45492 | F10001: Mouse | G10001: 4 | H10001: 5 | I10001: 190 | J10001: Debit Card | K10001: No

Sheet Working_Sheet
A1: Order_ID | B1: Customer_Name | C1: First_Name | D1: Last_Name | E1: Customer_Email | F1: City | G1: Order_Date | H1: Product | I1: Quantity | J1: Per Unit Cost | K1: Discount(%) | L1: Total Cost | M1: Total Sales | N1: Discounted Amount | O1: Payment_Method | P1: Shipped
A2: bdd640fb-0667-4ad1-9c80-317fa3b1799d | B2: Daniel Doyle | C2: Daniel | D2: Doyle | E2: garzaanthony@example.org | F2: East William | G2: 45411 | H2: Smartphone | I2: 3 | J2: =L2/I2 -> 800 | K2: 5 | L2: =M2/(1-K2/100) -> 2400 | M2: 2280 | N2: =Table2[[#This Row],[Total Cost]]-Table2[[#This Row],[Total Sales]] -> 120 | O2: Credit Card | P2: Yes
A3: b38a088c-a65e-4389-b74d-0fb132e70629 | B3: Connie Lawrence | C3: Connie | D3: Lawrence | E3: blakeerik@example.com | F3: Joshuaborough | G3: 45752 | H3: Keyboard | I3: 4 | J3: =L3/I3 -> 100 | K3: 0 | L3: =M3/(1-K3/100) -> 400 | M3: 400 | N3: =Table2[[#This Row],[Total Cost]]-Table2[[#This Row],[Total Sales]] -> 0 | O3: Debit Card | P3: Yes
A4: 6142ea7d-17be-4111-9a2a-73ed562b0f79 | B4: Ryan Munoz | C4: Ryan | D4: Munoz | E4: blairamanda@example.com | F4: New Kellystad | G4: 45613 | H4: Monitor | I4: 3 | J4: =L4/I4 -> 300 | K4: 0 | L4: =M4/(1-K4/100) -> 900 | M4: 900 | N4: =Table2[[#This Row],[Total Cost]]-Table2[[#This Row],[Total Sales]] -> 0 | O4: Debit Card | P4: Yes
A5: a9488d99-0bbb-4599-91ce-5dd2b45ed1f0 | B5: Dylan Miller | C5: Dylan | D5: Miller | E5: michellejames@example.com | F5: Franciscostad | G5: 45478 | H5: Smartphone | I5: 1 | J5: =L5/I5 -> 800 | K5: 5 | L5: =M5/(1-K5/100) -> 800 | M5: 760 | N5: =Table2[[#This Row],[Total Cost]]-Table2[[#This Row],[Total Sales]] -> 40 | O5: Google Pay | P5: Yes
A6: aefcfad8-efc8-4849-b3aa-7efe4458a885 | B6: Lisa Jackson | C6: Lisa | D6: Jackson | E6: frankgray@example.net | F6: Lake Mark | G6: 45683 | H6: Smartphone | I6: 2 | J6: =L6/I6 -> 800 | K6: 0 | L6: =M6/(1-K6/100) -> 1600 | M6: 1600 | N6: =Table2[[#This Row],[Total Cost]]-Table2[[#This Row],[Total Sales]] -> 0 | O6: Google Pay | P6: Yes
A7: 0837b8a3-d261-47ab-baa2-e4f90e51f30d | B7: Jennifer Jones | C7: Jennifer | D7: Jones | E7: jason76@example.net | F7: Thomasberg | G7: 45492 | H7: Desk Chair | I7: 2 | J7: =L7/I7 -> 200 | K7: 0 | L7: =M7/(1-K7/100) -> 400 | M7: 400 | N7: =Table2[[#This Row],[Total Cost]]-Table2[[#This Row],[Total Sales]] -> 0 | O7: Credit Card | P7: Yes
A8: bf3c4c06-4343-48bc-89fa-6a688fb5d27b | B8: Stephanie Ross | C8: Stephanie | D8: Ross | E8: wendytaylor@example.com | F8: Port Brandonville | G8: 45457 | H8: Laptop | I8: 1 | J8: =L8/I8 -> 1200 | K8: 5 | L8: =M8/(1-K8/100) -> 1200 | M8: 1140 | N8: =Table2[[#This Row],[Total Cost]]-Table2[[#This Row],[Total Sales]] -> 60 | O8: Credit Card | P8: Yes
A9: 6c12ace8-ae34-4454-8ac5-b68c28f49481 | B9: Janice Carlson | C9: Janice | D9: Carlson | E9: jrice@example.org | F9: Lake Nicoleview | G9: 45683 | H9: Monitor | I9: 1 | J9: =L9/I9 -> 300 | K9: 0 | L9: =M9/(1-K9/100) -> 300 | M9: 300 | N9: =Table2[[#This Row],[Total Cost]]-Table2[[#This Row],[Total Sales]] -> 0 | O9: Debit Card | P9: Yes
A10: 6f4cc69a-4b22-4308-9c8e-aee95715bd6f | B10: Aaron Bowen | C10: Aaron | D10: Bowen | E10: teresa28@example.org | F10: Meaganhaven | G10: 45624 | H10: External Hard Drive | I10: 3 | J10: =L10/I10 -> 90 | K10: 0 | L10: =M10/(1-K10/100) -> 270 | M10: 270 | N10: =Table2[[#This Row],[Total Cost]]-Table2[[#This Row],[Total Sales]] -> 0 | O10: Google Pay | P10: Yes
A11: 295b4715-c333-4861-9fb8-d16c2720797d | B11: Paula Moreno | C11: Paula | D11: Moreno | E11: georgetracy@example.org | F11: Natashaport | G11: 45489 | H11: Laptop | I11: 4 | J11: =L11/I11 -> 1200 | K11: 0 | L11: =M11/(1-K11/100) -> 4800 | M11: 4800 | N11: =Table2[[#This Row],[Total Cost]]-Table2[[#This Row],[Total Sales]] -> 0 | O11: Google Pay | P11: Yes
A12: f26b4776-913e-4de2-a0c5-3cb83da9c2a9 | B12: Nicholas Cabrera | C12: Nicholas | D12: Cabrera | E12: davidalvarez@example.net | F12: West Allison | G12: 45624 | H12: Monitor | I12: 3 | J12: =L12/I12 -> 300 | K12: 5 | L12: =M12/(1-K12/100) -> 900 | M12: 855 | N12: =Table2[[#This Row],[Total Cost]]-Table2[[#This Row],[Total Sales]] -> 45 | O12: Google Pay | P12: Yes
A13: 8a0f4efb-edcd-465e-b638-6821f6e07cc0 | B13: Melissa Marquez | C13: Melissa | D13: Marquez | E13: pcarney@example.com | F13: Lammouth | G13: 45446 | H13: Desk Chair | I13: 4 | J13: =L13/I13 -> 200 | K13: 0 | L13: =M13/(1-K13/100) -> 800 | M13: 800 | N13: =Table2[[#This Row],[Total Cost]]-Table2[[#This Row],[Total Sales]] -> 0 | O13: Debit Card | P13: Yes
... A10001: 6b376ab7-babe-4a22-b09d-01d5164cb33f | B10001: Charles Riley | C10001: Charles | D10001: Riley | E10001: montoyanancy@example.org | F10001: North Williamchester | G10001: 45492 | H10001: Mouse | I10001: 4 | J10001: =L10001/I10001 -> 50 | K10001: 5 | L10001: =M10001/(1-K10001/100) -> 200 | M10001: 190 | N10001: =Table2[[#This Row],[Total Cost]]-Table2[[#This Row],[Total Sales]] -> 10 | O10001: Debit Card | P10001: No

Sheet KPI
F1: KEY PERFORMANCE INDICATOR
F2: Total Order | G2: =COUNT(Working_Sheet!I2:I10001) -> 10000
F3: Order Shipped | G3: =COUNTIF(Working_Sheet!P2:P10001,"Yes") -> 9038
F4: Order Not Shipped | G4: =COUNTIF(Working_Sheet!P2:P10001,"NO") -> 962
F5: Shipping Rate % | G5: =G3/G2*100 -> 90.38
F6: Total Cost | G6: =SUM(Working_Sheet!L2:L10001) -> 8367270
F7: Total Sales | G7: =SUM(Working_Sheet!M2:M10001) -> 8095046.5
F8: Discount Total | G8: =G6-G7 -> 272223.5
F9: Average Sales | G9: =G7/G2 -> 809.50465

Sheet Pivot_table
A1: PIVOT TABLE
A5: Product | B5: Sum of Total Cost | C5: Sum of Total Sales | D5: Sum of Discounted Amount | F5: Product | G5: Sum of Quantity | I5: Payment_Method | J5: Sum of Total Sales
A6: Desk Chair | B6: 583800 | C6: 564780 | D6: -19020 | F6: Desk Chair | G6: 2919 | I6: Apple Pay | J6: 1564371
A7: External Hard Drive | B7: 251550 | C7: 243346.5 | D7: -8203.5 | F7: External Hard Drive | G7: 2795 | I7: Credit Card | J7: 1610284
A8: Headphones | B8: 424800 | C8: 411630 | D8: -13170 | F8: Headphones | G8: 2832 | I8: Debit Card | J8: 1647348.5
A9: Keyboard | B9: 270600 | C9: 261600 | D9: -9000 | F9: Keyboard | G9: 2706 | I9: Google Pay | J9: 1616808
A10: Laptop | B10: 3280800 | C10: 3174900 | D10: -105900 | F10: Laptop | G10: 2734 | I10: PayPal | J10: 1656235
A11: Monitor | B11: 781500 | C11: 754875 | D11: -26625 | F11: Monitor | G11: 2605 | I11: Grand Total | J11: 8095046.5
A12: Mouse | B12: 139300 | C12: 134645 | D12: -4655 | F12: Mouse | G12: 2786
A13: Smartphone | B13: 2292800 | C13: 2218400 | D13: -74400 | F13: Smartphone | G13: 2866
A14: Webcam | B14: 342120 | C14: 330870 | D14: -11250 | F14: Webcam | G14: 2851
A15: Grand Total | B15: 8367270 | C15: 8095046.5 | D15: -272223.5 | F15: Grand Total | G15: 25094

Sheet Dashboard
A1: E-COMMERCE DASHBOARD
